pyrestoolbox/__init__.py
pyrestoolbox/brine/__init__.py
pyrestoolbox/brine/brine.py
pyrestoolbox/brine/__pycache__/__init__.cpython-39.pyc
pyrestoolbox/brine/__pycache__/brine.cpython-39.pyc
pyrestoolbox/classes/__init__.py
pyrestoolbox/classes/classes.py
pyrestoolbox/classes/__pycache__/__init__.cpython-39.pyc
pyrestoolbox/classes/__pycache__/classes.cpython-39.pyc
pyrestoolbox/constants/__init__.py
pyrestoolbox/constants/constants.py
pyrestoolbox/constants/__pycache__/__init__.cpython-39.pyc
pyrestoolbox/constants/__pycache__/constants.cpython-39.pyc
pyrestoolbox/docs/brine.rst
pyrestoolbox/docs/changelist.rst
pyrestoolbox/docs/gas.rst
pyrestoolbox/docs/layer.rst
pyrestoolbox/docs/library.rst
pyrestoolbox/docs/oil.rst
pyrestoolbox/docs/simtools.rst
pyrestoolbox/docs/img/bot.png
pyrestoolbox/docs/img/bot_PVTO.png
pyrestoolbox/docs/img/bot_img.png
pyrestoolbox/docs/img/dry_gas.png
pyrestoolbox/docs/img/grid_sat_df.png
pyrestoolbox/docs/img/influence.png
pyrestoolbox/docs/img/properties_df.png
pyrestoolbox/docs/img/sgof.png
pyrestoolbox/docs/img/swof.png
pyrestoolbox/gas/__init__.py
pyrestoolbox/gas/gas.py
pyrestoolbox/gas/__pycache__/__init__.cpython-39.pyc
pyrestoolbox/gas/__pycache__/gas.cpython-39.pyc
pyrestoolbox/layer/__init__.py
pyrestoolbox/layer/layer.py
pyrestoolbox/library/__init__.py
pyrestoolbox/library/component_library.xlsx
pyrestoolbox/library/library.py
pyrestoolbox/oil/__init__.py
pyrestoolbox/oil/oil.py
pyrestoolbox/oil/__pycache__/__init__.cpython-39.pyc
pyrestoolbox/oil/__pycache__/oil.cpython-39.pyc
pyrestoolbox/shared_fns/__init__.py
pyrestoolbox/shared_fns/shared_fns.py
pyrestoolbox/shared_fns/__pycache__/__init__.cpython-39.pyc
pyrestoolbox/shared_fns/__pycache__/shared_fns.cpython-39.pyc
pyrestoolbox/simtools/__init__.py
pyrestoolbox/simtools/simtools.py
pyrestoolbox/validate/__init__.py
pyrestoolbox/validate/validate.py
pyrestoolbox/validate/__pycache__/__init__.cpython-39.pyc
pyrestoolbox/validate/__pycache__/validate.cpython-39.pyc
pyrestoolbox-2.1.4.dist-info/licenses/LICENSE
pyrestoolbox-2.1.4.dist-info/METADATA
pyrestoolbox-2.1.4.dist-info/WHEEL
pyrestoolbox-2.1.4.dist-info/top_level.txt
pyrestoolbox-2.1.4.dist-info/RECORD
