Metadata-Version: 2.4
Name: pyrestoolbox
Version: 2.1.4
Summary: pyResToolbox - A collection of Reservoir Engineering Utilities
Home-page: https://github.com/mwburgoyne/pyResToolbox
Author: Mark W. Burgoyne
Author-email: mark.w.burgoyne@gmail.com
License: GNU General Public License v3 or later (GPLv3+)
Keywords: restoolbox,petroleum,reservoir
Classifier: Programming Language :: Python :: 3
Classifier: License :: OSI Approved :: GNU General Public License v3 or later (GPLv3+)
Classifier: Operating System :: OS Independent
License-File: LICENSE
Requires-Dist: requests
Requires-Dist: numpy
Requires-Dist: scipy
Requires-Dist: pandas
Requires-Dist: tabulate
Requires-Dist: gwr_inversion
Requires-Dist: mpmath
Requires-Dist: openpyxl
Requires-Dist: setuptools
Dynamic: author
Dynamic: author-email
Dynamic: description
Dynamic: description-content-type
Dynamic: home-page
Dynamic: keywords
Dynamic: license
Dynamic: license-file
Dynamic: requires-dist
Dynamic: summary
